theauditor/.gitattributes
theauditor/__init__.py
theauditor/build_hooks.py
theauditor/cli.py
theauditor/framework_detector.py
theauditor/framework_registry.py
theauditor/universal_detector.py
theauditor/venv_install.py
theauditor/vulnerability_scanner.py
theauditor/workset.py
theauditor/MachineL/__init__.py
theauditor/MachineL/cli.py
theauditor/MachineL/features.py
theauditor/MachineL/impact_analyzer.py
theauditor/MachineL/intelligence.py
theauditor/MachineL/loaders.py
theauditor/MachineL/models.py
theauditor/agents/AGENTS.md
theauditor/agents/dataflow.md
theauditor/agents/planning.md
theauditor/agents/refactor.md
theauditor/agents/security.md
theauditor/agents/commands/dataflow.md
theauditor/agents/commands/impact.md
theauditor/agents/commands/planning.md
theauditor/agents/commands/refactor.md
theauditor/agents/commands/security.md
theauditor/agents/commands/start.md
theauditor/ast_extractors/__init__.py
theauditor/ast_extractors/ast_parser.py
theauditor/ast_extractors/base.py
theauditor/ast_extractors/bash_impl.py
theauditor/ast_extractors/go_impl.py
theauditor/ast_extractors/hcl_impl.py
theauditor/ast_extractors/js_helper_templates.py
theauditor/ast_extractors/js_semantic_parser.py
theauditor/ast_extractors/module_resolver.py
theauditor/ast_extractors/python_impl.py
theauditor/ast_extractors/rust_impl.py
theauditor/ast_extractors/javascript/README.md
theauditor/ast_extractors/javascript/__init__.py
theauditor/ast_extractors/javascript/package-lock.json
theauditor/ast_extractors/javascript/package.json
theauditor/ast_extractors/javascript/package.json.bak.1
theauditor/ast_extractors/javascript/tsconfig.json
theauditor/ast_extractors/javascript/dist/__init__.py
theauditor/ast_extractors/javascript/src/fidelity.test.ts
theauditor/ast_extractors/javascript/src/fidelity.ts
theauditor/ast_extractors/javascript/src/main.ts
theauditor/ast_extractors/javascript/src/schema.ts
theauditor/ast_extractors/javascript/src/test_extractor.ts
theauditor-2.0.4rc1.dist-info/METADATA
theauditor-2.0.4rc1.dist-info/WHEEL
theauditor-2.0.4rc1.dist-info/entry_points.txt
theauditor-2.0.4rc1.dist-info/licenses/LICENSE
theauditor-2.0.4rc1.dist-info/licenses/NOTICE_OF_INTELLECTUAL_PROPERTY.md
theauditor-2.0.4rc1.dist-info/RECORD
