Metadata-Version: 2.4
Name: theauditor
Version: 2.0.4rc1
Summary: Offline, air-gapped CLI for repo indexing, evidence checking, and task running
Author: TheAuditor Team
License: AGPL-3.0
License-File: LICENSE
License-File: NOTICE_OF_INTELLECTUAL_PROPERTY.md
Requires-Python: >=3.14
Requires-Dist: click==8.3.1
Requires-Dist: loguru==0.7.3
Requires-Dist: rich>=14.2.0
Provides-Extra: all
Requires-Dist: bandit==1.9.2; extra == 'all'
Requires-Dist: beautifulsoup4>=4.14.3; extra == 'all'
Requires-Dist: black==25.12.0; extra == 'all'
Requires-Dist: dockerfile-parse==2.0.1; extra == 'all'
Requires-Dist: graphql-core==3.2.7; extra == 'all'
Requires-Dist: httpx>=0.28.1; extra == 'all'
Requires-Dist: joblib==1.5.3; extra == 'all'
Requires-Dist: json5==0.12.1; extra == 'all'
Requires-Dist: libcst==1.8.6; extra == 'all'
Requires-Dist: markdownify>=1.2.2; extra == 'all'
Requires-Dist: mypy==1.19.1; extra == 'all'
Requires-Dist: networkx==3.6.1; extra == 'all'
Requires-Dist: numpy==2.4.0; extra == 'all'
Requires-Dist: pydantic==2.12.5; extra == 'all'
Requires-Dist: pygit2>=1.19.0; extra == 'all'
Requires-Dist: pylint==4.0.4; extra == 'all'
Requires-Dist: pytest-cov>=7.0.0; extra == 'all'
Requires-Dist: pytest-xdist>=3.8.0; extra == 'all'
Requires-Dist: pytest==9.0.2; extra == 'all'
Requires-Dist: pyyaml==6.0.3; extra == 'all'
Requires-Dist: ruff==0.14.10; extra == 'all'
Requires-Dist: scikit-learn==1.8.0; extra == 'all'
Requires-Dist: sqlparse==0.5.5; extra == 'all'
Requires-Dist: tree-sitter-language-pack==0.13.0; extra == 'all'
Requires-Dist: tree-sitter==0.25.2; extra == 'all'
Provides-Extra: dev
Requires-Dist: bandit==1.9.2; extra == 'dev'
Requires-Dist: black==25.12.0; extra == 'dev'
Requires-Dist: libcst==1.8.6; extra == 'dev'
Requires-Dist: mypy==1.19.1; extra == 'dev'
Requires-Dist: pylint==4.0.4; extra == 'dev'
Requires-Dist: pytest-cov>=7.0.0; extra == 'dev'
Requires-Dist: pytest-xdist>=3.8.0; extra == 'dev'
Requires-Dist: pytest==9.0.2; extra == 'dev'
Requires-Dist: ruff==0.14.10; extra == 'dev'
Provides-Extra: runtime
Requires-Dist: beautifulsoup4>=4.14.3; extra == 'runtime'
Requires-Dist: dockerfile-parse==2.0.1; extra == 'runtime'
Requires-Dist: graphql-core==3.2.7; extra == 'runtime'
Requires-Dist: httpx>=0.28.1; extra == 'runtime'
Requires-Dist: joblib==1.5.3; extra == 'runtime'
Requires-Dist: json5==0.12.1; extra == 'runtime'
Requires-Dist: markdownify>=1.2.2; extra == 'runtime'
Requires-Dist: networkx==3.6.1; extra == 'runtime'
Requires-Dist: numpy==2.4.0; extra == 'runtime'
Requires-Dist: pydantic==2.12.5; extra == 'runtime'
Requires-Dist: pygit2>=1.19.0; extra == 'runtime'
Requires-Dist: pyyaml==6.0.3; extra == 'runtime'
Requires-Dist: scikit-learn==1.8.0; extra == 'runtime'
Requires-Dist: sqlparse==0.5.5; extra == 'runtime'
Requires-Dist: tree-sitter-language-pack==0.13.0; extra == 'runtime'
Requires-Dist: tree-sitter==0.25.2; extra == 'runtime'
